tempMail2.py
tempMail2-1.0.2.dist-info/METADATA
tempMail2-1.0.2.dist-info/RECORD
tempMail2-1.0.2.dist-info/WHEEL
tempMail2-1.0.2.dist-info/top_level.txt
