Metadata-Version: 2.1
Name: tempMail2
Version: 1.0.2
Summary: Python wrapper for online service which provides temporary email address: https://temp-mail.org/ V2
Home-page: https://github.com/CITGuru/tempmail
Author: Oyetoke Toby
Author-email: oyetoketoby80@gmail.com
License: MIT
Download-URL: https://github.com/CITGuru/tempmail/archive/1.0.0.tar.gz
Keywords: temporary temp mail email address wrapper api anon anonymous secure free disposable
Platform: UNKNOWN
Classifier: Development Status :: 5 - Production/Stable
Classifier: Intended Audience :: Developers
Classifier: Operating System :: OS Independent
Classifier: Programming Language :: Python
Classifier: Programming Language :: Python :: 2.6
Classifier: Programming Language :: Python :: 2.7
Classifier: Programming Language :: Python :: 3.6
Classifier: Topic :: Internet :: WWW/HTTP
Requires-Dist: requests
